APB_sin.sv
module APB_sin
#(parameter control_reg_ADDR = 4'h0, // адрес контрольного регистра
  parameter output_reg_ADDR = 4'h4)  // адрес регистра, где хранится значение sin
(
    input wire PWRITE,            // сигнал, выбирающий режим записи или чтения (1 - запись, 0 - чтение)
    input wire PCLK,              // сигнал синхронизации
    input wire PSEL,              // сигнал выбора переферии 
    input wire [31:0] PADDR,      // Адрес регистра
    input wire [31:0] PWDATA,     // Данные для записи в регистр
    output reg [31:0] PRDATA = 0,        // Данные, прочитанные из регистра
    input wire PENABLE,           // сигнал разрешения
    output reg PREADY = 0         // сигнал готовности (флаг того, что всё сделано успешно)
);


reg  [31:0] control_reg  = 0; // регистр для записи значения x, где x принимает значения 0,1,2,3....
reg  [31:0] output_reg   = 0; // регистр для хранения результата после вычисления функции sin(x) 


always @(posedge PCLK) 
begin
    if (PSEL && !PWRITE && PENABLE) // Чтение из регистров 
     begin
        case(PADDR)
         4'h0: PRDATA <= control_reg; // чтение по адресу контрольного регистра
         4'h4: PRDATA <= output_reg;  // чтение по адресу выходного регистра
        endcase
        PREADY <= 1'd1; // поднимаем флаг заверешения операции
     end

     else if(PSEL && PWRITE && PENABLE) // запись производится только в контрольный регистр, который хранит значение шага pi/4
     begin
      if(PADDR == control_reg_ADDR)
      begin
        control_reg <= PWDATA;
        PREADY <= 1'd1;    // поднимаем флаг заверешения операции
      end
     end
   
   if (PREADY) // сбрасываем PREADY после выполнения записи или чтения
    begin
      PREADY <= !PREADY;
    end
    
  end

always @(control_reg) begin // вычисление значения sin(x)
 
    if(control_reg% 4 == 0) // если угол = pi*k (tg(pi*k)==0)
    begin
      output_reg <= 0;
    end

    else if((control_reg)%8 == 2) // если угол = pi/2 + 2pi*k (90 градусов)
    begin
      output_reg <= 1;
    end

      else if((control_reg)%8 == 6) // если угол = 3pi/2 + 2pi*k (270 градусов)
    begin
      output_reg <= ~(32'b00000000000000000000000000000001); // обратный код числа -1
    end

    else if(((control_reg)%8 == 1) || ((control_reg)%8 == 3)) // если угол = 3pi/4 + 2pi*k или pi/4 + 2pi*k (45 или 135 градусов)
    begin
      output_reg <= (32'b00111111001101010000010011110011); // sqrt(2)/2
    end

    else if(((control_reg)%8 == 5) || ((control_reg)%8 == 7)) // если угол = -3pi/4 + 2pi*k или -pi/4 + 2pi*k (135 или 315 градусов)
    begin
      output_reg <= ~(32'b00111111001101010000010011110011); // -sqrt(2)/2
    end

    else // иначе
    begin
      output_reg <= 32'b01111111111111111111111111111111; // очень большое значение
    end
  
end

//iverilog -g2012 -o APB_sin.vvp APB_sin_tb.sv
//vvp APB_sin.vvp
endmodule

APB_master.sv
module APB_master
(
    input wire PCLK,                    // сигнал синхронизации
    input wire PWRITE_MASTER,           // сигнал, выбирающий режим записи или чтения (1 - запись, 0 - чтение)
    output reg PSEL = 0,                // сигнал выбора переферии 
    input wire [31:0] PADDR_MASTER,     // Адрес регистра
    input wire [31:0] PWDATA_MASTER,    // Данные для записи в регистр
    output reg [31:0] PRDATA_MASTER = 0,// Данные, прочитанные из слейва
    output reg PENABLE = 0,             // сигнал разрешения, формирующийся в мастер APB
    input wire PRESET,                  // сигнал сброса
    input wire PREADY,                  // сигнал готовности (флаг того, что всё сделано успешно)
    output reg [31:0] PADDR = 0,        // адрес, который мы будем передавать в слейв
    output reg [31:0] PWDATA = 0,       // данные, которые будут передаваться в слейв,
    input  wire [31:0] PRDATA,          // данные, прочтённые с слейва
    output reg PWRITE = 0               // сигнал записи или чтения на вход слейва
);

task apb_write; // функция записи
input  [31:0] inp_addr;
 input  [31:0] inp_data;
begin
  PSEL = 1'd1;        // поднимаем флаг выбора устройства
  PADDR = inp_addr;   // передаем адрес на входе мастера в слейв
  PWDATA = inp_data;  // передаём данные в слейв
  PWRITE = 1'd1;      // ставим сигнал записи
  PENABLE = 1'd1;     // выдаём разрешение на выполнение действий

  if(PREADY)
   begin
     PSEL = !PSEL;        // убираем сигнал psel
     PENABLE = !PENABLE; // убираем  сигнал PENABLE
   end
end
endtask

task apb_read; //функция чтения из слейва
input [31:0] inp_addr;
begin
  if(!PREADY)
  begin
    PADDR = inp_addr; // передаем адрес на входе мастера в слейв
    PWRITE = 1'd0;
    PSEL = 1'd1;
    PENABLE = 1'd1;
  end
  
  else if(PREADY)
   begin
     PSEL = !PSEL;
     PENABLE = !PENABLE;
   end
end
endtask

// циклы записи и чтения интерфейса APB
always @(posedge PCLK) 
begin
    if(PRESET) // если поднят сигнал сброса
    begin
      PADDR <= 32'b0;
      PWDATA <= 32'b0;
      PWRITE <= 1'b0;
      PSEL <= 1'b0;
      PENABLE <= 1'b0;
      PRDATA_MASTER <= 1'b0;
    end

    else if (!PWRITE_MASTER) // Чтение из регистров 
     begin
        apb_read(PADDR_MASTER); // вызов фунции чтения
     end
    else if (PWRITE_MASTER) // Запись в регистры
     begin
        apb_write(PADDR_MASTER, PWDATA_MASTER);
     end
  end

always @(posedge PREADY) // если pready поднялся в 1
begin
  if (!PWRITE_MASTER)     // если выбрана операция чтение
    begin
     PRDATA_MASTER <=PRDATA; // передаём данные на выход apb мастера
    end
end
endmodule

APB_sin_tb.sv
`include "APB_master.sv"
`include "APB_sin.sv"
module APB_sin_tb;



reg PCLK = 0;                   // сигнал синхронизации
reg PWRITE_MASTER = 0;          // сигнал, выбирающий режим записи или чтения (1 - запись, 0 - чтение)
wire PSEL;                      // сигнал выбора переферии
//reg PSEL = 0; 
reg [31:0] PADDR_MASTER = 0;    // Адрес регистра
reg [31:0] PWDATA_MASTER = 0;   // Данные для записи в регистр
wire [31:0] PRDATA_MASTER;       // Данные, прочитанные из слейва
wire PENABLE;                    // сигнал разрешения, формирующийся в мастер APB
reg PRESET = 0;                   // сигнал сброса
wire PREADY;                      // сигнал готовности (флаг того, что всё сделано успешно)
wire [31:0] PADDR;                // адрес, который мы будем передавать в слейв
wire [31:0] PWDATA;               // данные, которые будут передаваться в слейв,
wire [31:0] PRDATA ;              // данные, прочтённые с слейва
wire PWRITE;                      // сигнал записи или чтения на вход слейва

APB_master APB_master_1 (
    .PCLK(PCLK),
    .PWRITE_MASTER(PWRITE_MASTER),
    .PSEL(PSEL),
    .PADDR_MASTER(PADDR_MASTER),
    .PWDATA_MASTER(PWDATA_MASTER),
    .PRDATA_MASTER(PRDATA_MASTER),
    .PENABLE(PENABLE),
    .PRESET(PRESET),
    .PREADY(PREADY),
    .PADDR(PADDR),
    .PWDATA(PWDATA),
    .PRDATA(PRDATA),
    .PWRITE(PWRITE)
);

APB_sin APB_sin_1 (
    .PWRITE(PWRITE),
    .PSEL(PSEL),
    .PADDR(PADDR),
    .PWDATA(PWDATA),
    .PRDATA(PRDATA),
    .PENABLE(PENABLE),
    .PREADY(PREADY),
    .PCLK(PCLK)
);



always #200 PCLK = ~PCLK; // генерация входного сигнала Pclk

initial begin
    
PCLK = 0;
@(posedge PCLK);
PWRITE_MASTER = 1;           // выбираем запись
PWDATA_MASTER = 32'd0;       // в данные для записи записываем n = 0 ; на выходе должно быть значение 0
PADDR_MASTER = 0;            // выбираем адрес регистра control_reg
@(posedge PCLK);
@(posedge PCLK);

PWRITE_MASTER = 1;          // выбираем запись
PWDATA_MASTER = 32'd1;     // в данные для записи записываем n = 1 ; на выходе должно быть значение sqrt(2)/2
PADDR_MASTER = 0;           // выбираем адрес регистра control_reg
@(posedge PCLK);
@(posedge PCLK);

PWRITE_MASTER = 1;          // выбираем запись
PWDATA_MASTER = 32'd2;     // в данные для записи записываем n = 2 ; на выходе должно быть значение 1
PADDR_MASTER = 0;           // выбираем адрес регистра control_reg
@(posedge PCLK);
@(posedge PCLK);

PWRITE_MASTER = 1;          // выбираем запись
PWDATA_MASTER = 32'd3;     // в данные для записи записываем n = 3 ; на выходе должно быть значение sqrt(2)/2
PADDR_MASTER = 0;           // выбираем адрес регистра control_reg
@(posedge PCLK);
@(posedge PCLK);

PWRITE_MASTER = 1;          // выбираем запись
PWDATA_MASTER = 32'd4;     // в данные для записи записываем n = 4 ; на выходе должно быть значение 0
PADDR_MASTER = 0;           // выбираем адрес регистра control_reg
@(posedge PCLK);
@(posedge PCLK);

PWRITE_MASTER = 1;          // выбираем запись
PWDATA_MASTER = 32'd5;     // в данные для записи записываем n = 5 ; на выходе должно быть значение -sqrt(2)/2
PADDR_MASTER = 0;           // выбираем адрес регистра control_reg
@(posedge PCLK);
@(posedge PCLK);

PWRITE_MASTER = 1;          // выбираем запись
PWDATA_MASTER = 32'd6;     // в данные для записи записываем n = 6 ; на выходе должно быть значение -1
PADDR_MASTER = 0;           // выбираем адрес регистра control_reg
@(posedge PCLK);
@(posedge PCLK);

PWRITE_MASTER = 1;          // выбираем запись
PWDATA_MASTER = 32'd7;     // в данные для записи записываем n = 7 ; на выходе должно быть значение -sqrt(2)/2
PADDR_MASTER = 0;           // выбираем адрес регистра control_reg
@(posedge PCLK);
@(posedge PCLK);


PWRITE_MASTER = 1;          // выбираем запись
PWDATA_MASTER = 32'd8;     // в данные для записи записываем n = 8 ; на выходе должно быть значение 0
PADDR_MASTER = 0;           // выбираем адрес регистра control_reg
@(posedge PCLK);
@(posedge PCLK);

PWRITE_MASTER = 1;          // выбираем запись
PWDATA_MASTER = 32'd9;     // в данные для записи записываем n = 9 ; на выходе должно быть значение sqrt(2)/2
PADDR_MASTER = 0;           // выбираем адрес регистра control_reg
@(posedge PCLK)
@(posedge PCLK);

PWRITE_MASTER = 0;          // выбираем Чтение
PADDR_MASTER = 0;           // выбираем адрес регистра control_reg
@(posedge PCLK);
@(posedge PCLK);

PWRITE_MASTER = 0;          // выбираем Чтение
PADDR_MASTER = 4;           // выбираем адрес регистра output_reg
@(posedge PCLK);
@(posedge PCLK);


 #500 $finish; // Заканчиваем симуляцию
end







initial begin
$dumpfile("APB_sin.vcd"); // создание файла для сохранения результатов симуляции
$dumpvars(0, APB_sin_tb); // установка переменных для сохранения в файле
$dumpvars;
end


endmodule

APB_sin.vcd
$date
	Wed Dec 27 21:59:19 2023
$end
$version
	Icarus Verilog
$end
$timescale
	1s
$end
$scope module APB_sin_tb $end
$var wire 32 ! PADDR [31:0] $end
$var wire 1 " PENABLE $end
$var wire 32 # PRDATA [31:0] $end
$var wire 32 $ PRDATA_MASTER [31:0] $end
$var wire 1 % PREADY $end
$var wire 1 & PSEL $end
$var wire 32 ' PWDATA [31:0] $end
$var wire 1 ( PWRITE $end
$var reg 32 ) PADDR_MASTER [31:0] $end
$var reg 1 * PCLK $end
$var reg 1 + PRESET $end
$var reg 32 , PWDATA_MASTER [31:0] $end
$var reg 1 - PWRITE_MASTER $end
$scope module APB_master_1 $end
$var wire 32 . PADDR_MASTER [31:0] $end
$var wire 1 / PCLK $end
$var wire 32 0 PRDATA [31:0] $end
$var wire 1 % PREADY $end
$var wire 1 1 PRESET $end
$var wire 32 2 PWDATA_MASTER [31:0] $end
$var wire 1 3 PWRITE_MASTER $end
$var reg 32 4 PADDR [31:0] $end
$var reg 1 5 PENABLE $end
$var reg 32 6 PRDATA_MASTER [31:0] $end
$var reg 1 7 PSEL $end
$var reg 32 8 PWDATA [31:0] $end
$var reg 1 9 PWRITE $end
$scope task apb_read $end
$var reg 32 : inp_addr [31:0] $end
$upscope $end
$scope task apb_write $end
$var reg 32 ; inp_addr [31:0] $end
$var reg 32 < inp_data [31:0] $end
$upscope $end
$upscope $end
$scope module APB_sin_1 $end
$var wire 32 = PADDR [31:0] $end
$var wire 1 / PCLK $end
$var wire 1 " PENABLE $end
$var wire 1 & PSEL $end
$var wire 32 > PWDATA [31:0] $end
$var wire 1 ( PWRITE $end
$var reg 32 ? PRDATA [31:0] $end
$var reg 1 @ PREADY $end
$var reg 32 A control_reg [31:0] $end
$var reg 32 B output_reg [31:0] $end
$upscope $end
$upscope $end
$scope module APB_sin_tb $end
$scope module APB_master_1 $end
$scope task apb_read $end
$upscope $end
$scope task apb_write $end
$upscope $end
$upscope $end
$scope module APB_sin_1 $end
$upscope $end
$upscope $end
$enddefinitions $end
#0
$dumpvars
b0 B
b0 A
0@
b0 ?
b0 >
b0 =
bx <
bx ;
bx :
09
b0 8
07
b0 6
05
b0 4
03
b0 2
01
b0 0
0/
b0 .
0-
b0 ,
0+
0*
b0 )
0(
b0 '
0&
0%
b0 $
b0 #
0"
b0 !
$end
#200
15
1"
19
1(
17
1&
b0 <
b0 ;
1-
13
1*
1/
#400
0*
0/
#600
1@
1%
1*
1/
#800
0*
0/
#1000
0@
0%
05
0"
07
0&
b1 ,
b1 2
1*
1/
#1200
0*
0/
#1400
15
1"
b1 8
b1 '
b1 >
17
1&
b1 <
1*
1/
#1600
0*
0/
#1800
b111111001101010000010011110011 B
1@
1%
b1 A
b10 ,
b10 2
1*
1/
#2000
0*
0/
#2200
0@
0%
05
0"
07
0&
b10 8
b10 '
b10 >
b10 <
1*
1/
#2400
0*
0/
#2600
15
1"
17
1&
b11 ,
b11 2
1*
1/
#2800
0*
0/
#3000
b1 B
1@
1%
b10 A
b11 8
b11 '
b11 >
b11 <
1*
1/
#3200
0*
0/
#3400
b111111001101010000010011110011 B
0@
0%
b11 A
05
0"
07
0&
b100 ,
b100 2
1*
1/
#3600
0*
0/
#3800
15
1"
b100 8
b100 '
b100 >
17
1&
b100 <
1*
1/
#4000
0*
0/
#4200
b0 B
1@
1%
b100 A
b101 ,
b101 2
1*
1/
#4400
0*
0/
#4600
0@
0%
05
0"
07
0&
b101 8
b101 '
b101 >
b101 <
1*
1/
#4800
0*
0/
#5000
15
1"
17
1&
b110 ,
b110 2
1*
1/
#5200
0*
0/
#5400
b11000000110010101111101100001100 B
1@
1%
b101 A
b110 8
b110 '
b110 >
b110 <
1*
1/
#5600
0*
0/
#5800
b11111111111111111111111111111110 B
0@
0%
b110 A
05
0"
07
0&
b111 ,
b111 2
1*
1/
#6000
0*
0/
#6200
15
1"
b111 8
b111 '
b111 >
17
1&
b111 <
1*
1/
#6400
0*
0/
#6600
b11000000110010101111101100001100 B
1@
1%
b111 A
b1000 ,
b1000 2
1*
1/
#6800
0*
0/
#7000
0@
0%
05
0"
07
0&
b1000 8
b1000 '
b1000 >
b1000 <
1*
1/
#7200
0*
0/
#7400
15
1"
17
1&
b1001 ,
b1001 2
1*
1/
#7600
0*
0/
#7800
b0 B
1@
1%
b1000 A
b1001 8
b1001 '
b1001 >
b1001 <
1*
1/
#8000
0*
0/
#8200
b111111001101010000010011110011 B
0@
0%
b1001 A
05
0"
07
0&
0-
03
1*
1/
#8400
0*
0/
#8600
15
1"
17
1&
09
0(
b0 :
1*
1/
#8800
0*
0/
#9000
b1001 6
b1001 $
1@
1%
b1001 ?
b1001 #
b1001 0
b100 )
b100 .
1*
1/
#9200
0*
0/
#9400
0@
0%
05
0"
07
0&
b100 :
1*
1/
#9600
0*
0/
#9800
15
1"
17
1&
b100 4
b100 !
b100 =
1*
1/
#10000
0*
0/
#10200
b111111001101010000010011110011 6
b111111001101010000010011110011 $
1@
1%
b111111001101010000010011110011 ?
b111111001101010000010011110011 #
b111111001101010000010011110011 0
1*
1/
